roms2schism/__init__.py
roms2schism/boundary.py
roms2schism/geometry.py
roms2schism/hotstart.py
roms2schism/interpolation.py
roms2schism/nudging.py
roms2schism/roms.py
roms2schism/roms2schism_bry.py
roms2schism/schism.py
roms2schism-0.9.2.dist-info/LICENSE
roms2schism-0.9.2.dist-info/METADATA
roms2schism-0.9.2.dist-info/WHEEL
roms2schism-0.9.2.dist-info/top_level.txt
roms2schism-0.9.2.dist-info/RECORD
