Metadata-Version: 2.1
Name: roms2schism
Version: 0.9.2
Summary: A Python package for creating SCHISM boundary condition forcing and hotstart files from ROMS output
Author-email: Ivica Janekovic <ivica.janekovic@uwa.edu.au>, Adrian Croucher <a.croucher@auckland.ac.nz>
License: GNU LESSER GENERAL PUBLIC LICENSE
Project-URL: repository, https://github.com/ivicajan/ROMS2SCHISM
Classifier: Programming Language :: Python :: 3
Classifier: License :: OSI Approved :: GNU Lesser General Public License v3 (LGPLv3)
Classifier: Operating System :: OS Independent
Requires-Python: >=3.6
License-File: LICENSE
Requires-Dist: progressbar2
Requires-Dist: netCDF4
Requires-Dist: numpy
Requires-Dist: scipy
Requires-Dist: matplotlib
